[
    {
        "question" : "¿Cómo se inició el dolor?",
        "type": 2,
        "choice1" : "No precisa",
        "choice2" : "Súbito",
        "choice3" : "Insidioso, crescendo",
        "choice4" : "Insidioso, no crescendo",
        "variable" : "typePainOnset",
        "priority" : false
    },
    {
        "question" : "¿Cuánto tiempo ha pasado desde el inicio del dolor hasta la consulta?",
        "type" : 1,
        "variable" : "timePainBegan2Present",
        "priority" : false
    },
    {
        "question" : "¿Cuál es el tipo de dolor que presenta el paciente?",
        "type" : 2,
        "choice1" : "Púlsatil",
        "choice2" : "Palpitante",
        "choice3" : "Opresivo",
        "choice4" : "Punzante",
        "choice5" : "Lancinante",
        "choice6" : "Penetrante",
        "variable" : "typePain",
        "priority" : true
    },
    {
        "question" : "Mencione la ubicación del dolor",
        "type" : 2,
        "choice1" : "Unilateral Izquierdo",
        "choice2" : "Unilateral Derecho",
        "choice3" : "Bilateral",
        "variable" : "ubicationPain",
        "priority" : true
    },
    {
        "question" : "Podría especificar la región del cerebro dónde se ubica el dolor?",
        "type" : 2,
        "choice1" : "Occipital",
        "choice2" : "Parietal",
        "choice3" : "Frontal",
        "choice4" : "Orbital",
        "choice5" : "Supraorbital",
        "choice6" : "Facial",
        "variable" : "specificUbicationPain",
        "priority" : false
    },
    {
        "question" : "Indique la intensidad del dolor",
        "type" : 1,
        "choice1" : "",
        "choice2" : "",
        "variable" : "intensityPain",
        "priority" : true
    }
]